<xml xmlns="https://developers.google.com/blockly/xml"><block type="component_event" id=";W]td;|a8uf#e2$GMyD%" x="-45" y="-339"><mutation xmlns="http://www.w3.org/1999/xhtml" component_name="Profile Screen" component_type="Screen" parent_id="undefined" event_id="Opens" was_updated="true"/><field name="component_id">74a9160a-dc38-424a-bb38-819421152d40</field><field name="event_id">Opens</field><statement name="input_do"><block type="controls_if" id="Fu+%~%?sDxU1msM$9qUS"><mutation else="1"/><value name="IF0"><block type="logic_compare" id="p)zoF,PeRzgS;h`]7UH2"><field name="OP">EQ</field><value name="A"><block type="variables_get_dynamic" id="UMm|;TXx/dlh:v$8Us{S"><field name="SCOPE">CLOUD</field><value name="NAME"><shadow type="text" id="a{CUP:L?WzHQ~fPgHcJK"><field name="TEXT">name</field></shadow><block type="variables_get" id="I$`T3dkvxRPmb|tmKGWN"><mutation xmlns="http://www.w3.org/1999/xhtml" saved_name="app variable session_id"/><field name="VAR">9e995ff8-a9a5-4978-b428-d429d0843a1d</field></block></value></block></value><value name="B"><block type="logic_null" id="J^u9)Jws#`N,ExTYfPi@"/></value></block></value><statement name="DO0"><block type="variables_set_dynamic" id="PJT?u2?$DaTRbcu92TJC"><field name="SCOPE">CLOUD</field><value name="NAME"><shadow type="text" id="]Qib:7bUltI^}E%gy,f7"><field name="TEXT">name</field></shadow><block type="variables_get" id="ubQ)A45hmb7lI|(D[EMG"><mutation xmlns="http://www.w3.org/1999/xhtml" saved_name="app variable session_id"/><field name="VAR">9e995ff8-a9a5-4978-b428-d429d0843a1d</field></block></value><value name="VALUE"><block type="object_create" id="yuP=CAbUx.XTTNG3xF$E"><mutation xmlns="http://www.w3.org/1999/xhtml" num_fields="5"><field name="Name"/><field name="Image"/><field name=""/><field name=""/><field name=""/></mutation><field name="field1">Name</field><field name="field2">Image</field><field name="field3">Email</field><field name="field4">ID</field><field name="field5">Sign_Up_Date</field><value name="field_input1"><block type="logic_null" id="r@WQ2yHBK#ir}T[ms]0C"/></value><value name="field_input2"><block type="logic_null" id="C^ODdSteyGKs9P_tr653"/></value><value name="field_input3"><block type="variables_get" id="Tll[)Dbx6$CXe2:UH?[}"><mutation xmlns="http://www.w3.org/1999/xhtml" saved_name="app variable session_email"/><field name="VAR">3ff69446-c265-4493-9e16-b8370040c234</field></block></value><value name="field_input4"><block type="variables_get" id="84a)-kxH7iV)^YBPRRd_"><mutation xmlns="http://www.w3.org/1999/xhtml" saved_name="app variable session_id"/><field name="VAR">9e995ff8-a9a5-4978-b428-d429d0843a1d</field></block></value><value name="field_input5"><block type="text_join" id="n,gscgav]iJI@g{$^b?}"><mutation items="5"/><value name="ADD0"><block type="device_current_date" id="XO3rGz8Ldt2(-X`VDBSy"><field name="TIME_PERIOD">MONTH</field></block></value><value name="ADD1"><block type="text" id="(eugwMXLu%o!Jn)vOL5P"><field name="TEXT">/</field></block></value><value name="ADD2"><block type="device_current_date" id=")ZXM4q}:;l~`Gd@$Cyjy"><field name="TIME_PERIOD">DAY_OF_MONTH</field></block></value><value name="ADD3"><block type="text" id="O.i|@db~tF#r!VD=uwG["><field name="TEXT">/</field></block></value><value name="ADD4"><block type="device_current_date" id="vip2OL}}Ri$UnFmGk5YA"><field name="TIME_PERIOD">YEAR</field></block></value></block></value></block></value></block></statement><statement name="ELSE"><block type="setter" id="lWR+6xcs%p@2y+#w@ase"><mutation xmlns="http://www.w3.org/1999/xhtml" component_name="Name_Label" parent_id="undefined"/><field name="component_id">1119e395-209d-48ff-b235-4454154bd5c4</field><field name="field_name">Text</field><value name="field_value"><shadow type="text" id="#)C-Noz}YZ2=i02/|7l`"><field name="TEXT">Label</field></shadow><block type="variables_get_dynamic" id="_x*`vlIZq@{*eECjbn)x"><field name="SCOPE">CLOUD</field><value name="NAME"><shadow type="text" id="m5.?kQ}.7lO8.Q+LbnzW"><field name="TEXT">name</field></shadow><block type="text_join" id="D;XJRp#|]^AJf@Otp];/"><mutation items="2"/><value name="ADD0"><block type="variables_get" id="gw(;~ad08(J0(!*u~p?h"><mutation xmlns="http://www.w3.org/1999/xhtml" saved_name="app variable session_id"/><field name="VAR">9e995ff8-a9a5-4978-b428-d429d0843a1d</field></block></value><value name="ADD1"><block type="text" id="7JuaRv1B0h{T7o#?6]:z"><field name="TEXT">/Name</field></block></value></block></value></block></value><next><block type="setter" id="]cUX;023jDYWlzI*d.#J"><mutation xmlns="http://www.w3.org/1999/xhtml" component_name="Profile_Pic" parent_id="undefined"/><field name="component_id">dd25b85d-4fa8-4729-ac41-0a5f4f772617</field><field name="field_name">Picture</field><value name="field_value"><shadow type="asset_get" id="SX:ZLi*+?8meNRfc{Mf+"><mutation xmlns="http://www.w3.org/1999/xhtml" previous_asset_name="" previous_asset_value="INVALID_ASSET"/><field name="ASSET">INVALID_ASSET</field></shadow><block type="variables_get_dynamic" id="B0fmTvyZC!=9b74lPKa`"><field name="SCOPE">CLOUD</field><value name="NAME"><shadow type="text" id="m5.?kQ}.7lO8.Q+LbnzW"><field name="TEXT">name</field></shadow><block type="text_join" id="CRW!aGLJ{V~$u|Ie,Lzc"><mutation items="2"/><value name="ADD0"><block type="variables_get" id=")avur%(~Qd|m3o}K:gZ^"><mutation xmlns="http://www.w3.org/1999/xhtml" saved_name="app variable session_id"/><field name="VAR">9e995ff8-a9a5-4978-b428-d429d0843a1d</field></block></value><value name="ADD1"><block type="text" id="%/qZH9+zlh81oHTvo..f"><field name="TEXT">/Image</field></block></value></block></value></block></value></block></next></block></statement></block></statement></block><block type="component_event" id="7*LI*]A0BDjfs7y{1u3@" x="906" y="126"><mutation xmlns="http://www.w3.org/1999/xhtml" component_name="Profile Screen" component_type="Screen" parent_id="undefined" event_id="Opens" was_updated="true"/><field name="component_id">74a9160a-dc38-424a-bb38-819421152d40</field><field name="event_id">Opens</field><statement name="input_do"><block type="setter" id="~ZGvFmcZAuQ439l2lt?0"><mutation xmlns="http://www.w3.org/1999/xhtml" component_name="AdMob_Banner2" parent_id="undefined"/><field name="component_id">5ab2894c-0ea6-4fcb-9b37-9b0520ce7044</field><field name="field_name">TestMode</field><value name="field_value"><shadow type="logic_boolean" id="ytrusrw|UDu`3Sv03emY"><field name="BOOL">TRUE</field></shadow></value><next><block type="setter" id="1@GN[n0ZXZaC7iWalC97"><mutation xmlns="http://www.w3.org/1999/xhtml" component_name="AdMob_Banner2" parent_id="undefined"/><field name="component_id">5ab2894c-0ea6-4fcb-9b37-9b0520ce7044</field><field name="field_name">Visible</field><value name="field_value"><shadow type="logic_boolean" id=")Sp$jJY-)`vUJ$2din?b"><field name="BOOL">TRUE</field></shadow></value></block></next></block></statement></block><block type="component_event" id="(ECb#p$|pHf[,ZULEGjl" x="32" y="235"><mutation xmlns="http://www.w3.org/1999/xhtml" component_name="Add_name" component_type="Button" parent_id="undefined" event_id="Click" was_updated="true"/><field name="component_id">82fbbfac-075c-4eef-a648-9a223b2f5ce9</field><field name="event_id">Click</field><statement name="input_do"><block type="setter" id="o;bB(#xq6!3]r1tn6`rL"><mutation xmlns="http://www.w3.org/1999/xhtml" component_name="Name Group" parent_id="undefined"/><field name="component_id">46670e5c-5463-4cb8-afde-fa64a561bc29</field><field name="field_name">Visible</field><value name="field_value"><shadow type="logic_boolean" id="HT9g(lWk`W65l=#z(xxR"><field name="BOOL">TRUE</field></shadow></value></block></statement></block><block type="component_event" id="!oYtYOPodGTb{@mtvgo}" x="385" y="226"><mutation xmlns="http://www.w3.org/1999/xhtml" component_name="Cancel_New_Name" component_type="Button" parent_id="undefined" event_id="Click" was_updated="true"/><field name="component_id">5ba87edf-560c-476f-a996-0bc130851273</field><field name="event_id">Click</field><statement name="input_do"><block type="setter" id=";DJ|p7.JA6F;d@RWfu{Z"><mutation xmlns="http://www.w3.org/1999/xhtml" component_name="Name Group" parent_id="undefined"/><field name="component_id">46670e5c-5463-4cb8-afde-fa64a561bc29</field><field name="field_name">Visible</field><value name="field_value"><shadow type="logic_boolean" id="M%%O}Q2d6ejEl[Cr}a()"><field name="BOOL">FALSE</field></shadow></value></block></statement></block><block type="component_event" id="TS$2r-I@!AVXEbO/SW9`" x="1" y="299"><mutation xmlns="http://www.w3.org/1999/xhtml" component_name="Save_Name" component_type="Button" parent_id="undefined" event_id="Click" was_updated="true"/><field name="component_id">b2e66e20-70b7-4292-98bc-f82f732bc9c2</field><field name="event_id">Click</field><statement name="input_do"><block type="controls_if" id="+Yz5J,ho%1m*yM7HDi_r"><mutation else="1"/><value name="IF0"><block type="text_isEmpty" id="*MRZX|kG+uew~Z0hya?]"><value name="VALUE"><shadow type="text" id="+tG1fsW/I|,{;jc::QyA"><field name="TEXT"/></shadow><block type="set_get" id="##MuaJDWcnu.adr(jn84"><mutation xmlns="http://www.w3.org/1999/xhtml" component_name="Name_Input" parent_id="undefined"/><field name="component_id">2486f817-5023-4cd5-ad26-950fe7827677</field><field name="field_name">Text</field></block></value></block></value><statement name="DO0"><block type="setter" id="2[[|bhRm@CMD$LX]:-BH"><mutation xmlns="http://www.w3.org/1999/xhtml" component_name="Profile Screen Error Label" parent_id="undefined"/><field name="component_id">4282b87d-6e30-4676-a6fe-507531ac775f</field><field name="field_name">Text</field><value name="field_value"><shadow type="text" id="]L$;-p#1EgS_91%P`?a4"><field name="TEXT">Name cannot be blank.</field></shadow></value></block></statement><statement name="ELSE"><block type="variables_set_dynamic" id="(`N6=F|D;m3{_PAo|DKh"><field name="SCOPE">CLOUD</field><value name="NAME"><shadow type="text" id="DUn@w(VZbDQ~+B[etM,U"><field name="TEXT">name</field></shadow><block type="text_join" id="7C`4PL?i5JL$^gtZi:1e"><mutation items="2"/><value name="ADD0"><block type="variables_get" id="Dem]w=5Q^Hi]KduCX$F6"><mutation xmlns="http://www.w3.org/1999/xhtml" saved_name="app variable session_id"/><field name="VAR">9e995ff8-a9a5-4978-b428-d429d0843a1d</field></block></value><value name="ADD1"><block type="text" id="m}/F!~mTxyKanVH#f,o*"><field name="TEXT">/Name</field></block></value></block></value><value name="VALUE"><block type="set_get" id="n_[Ue@XmHN3ofVdMEciY"><mutation xmlns="http://www.w3.org/1999/xhtml" component_name="Name_Input" parent_id="undefined"/><field name="component_id">2486f817-5023-4cd5-ad26-950fe7827677</field><field name="field_name">Text</field></block></value><next><block type="setter" id="{1:wfQ)RcT[la%fGDXm@"><mutation xmlns="http://www.w3.org/1999/xhtml" component_name="Name_Label" parent_id="undefined"/><field name="component_id">1119e395-209d-48ff-b235-4454154bd5c4</field><field name="field_name">Text</field><value name="field_value"><shadow type="text" id="#)C-Noz}YZ2=i02/|7l`"><field name="TEXT">Label</field></shadow><block type="variables_get_dynamic" id="E}Na|Q~FViehv$gL*jXl"><field name="SCOPE">CLOUD</field><value name="NAME"><shadow type="text" id="m5.?kQ}.7lO8.Q+LbnzW"><field name="TEXT">name</field></shadow><block type="text_join" id="o~wqjRJ/wol.@~Cm)![A"><mutation items="2"/><value name="ADD0"><block type="variables_get" id=")$Ky~t$UU`ao5ZrTmy|U"><mutation xmlns="http://www.w3.org/1999/xhtml" saved_name="app variable session_id"/><field name="VAR">9e995ff8-a9a5-4978-b428-d429d0843a1d</field></block></value><value name="ADD1"><block type="text" id="^Ng%Bee-J5_B!pwP76{?"><field name="TEXT">/Name</field></block></value></block></value></block></value><next><block type="setter" id="h~!VvV9NeI$#}Q_7m`Ue"><mutation xmlns="http://www.w3.org/1999/xhtml" component_name="Name Group" parent_id="undefined"/><field name="component_id">46670e5c-5463-4cb8-afde-fa64a561bc29</field><field name="field_name">Visible</field><value name="field_value"><shadow type="logic_boolean" id="Wh2H]Lz{sb3h^KfDZ]O:"><field name="BOOL">FALSE</field></shadow></value></block></next></block></next></block></statement></block></statement></block><block type="component_event" id="s5lC.0Z`0yC!KFV,`6@q" x="0" y="579"><mutation xmlns="http://www.w3.org/1999/xhtml" component_name="Add_image" component_type="Button" parent_id="undefined" event_id="Click" was_updated="true"/><field name="component_id">312882b9-14cc-4441-8192-42a3a1d7fb51</field><field name="event_id">Click</field><statement name="input_do"><block type="setter" id="C.Jyy+38A.kB8MDv|;1n"><mutation xmlns="http://www.w3.org/1999/xhtml" component_name="Image Group" parent_id="undefined"/><field name="component_id">494cdfac-e3d7-4df9-977c-4a9a8e71b920</field><field name="field_name">Visible</field><value name="field_value"><shadow type="logic_boolean" id=",=m^1-VxKZ^MrHAnLTsj"><field name="BOOL">TRUE</field></shadow></value></block></statement></block><block type="component_event" id="S8^R#+:Yv-fkXkg_TZ_y" x="386" y="577"><mutation xmlns="http://www.w3.org/1999/xhtml" component_name="Cancel_New_Image" component_type="Button" parent_id="undefined" event_id="Click" was_updated="true"/><field name="component_id">332f621d-930a-4df3-9c5b-c34c53a7519d</field><field name="event_id">Click</field><statement name="input_do"><block type="setter" id="YgQ$k;]iR/YtrWNp~E=v"><mutation xmlns="http://www.w3.org/1999/xhtml" component_name="Image Group" parent_id="undefined"/><field name="component_id">494cdfac-e3d7-4df9-977c-4a9a8e71b920</field><field name="field_name">Visible</field><value name="field_value"><shadow type="logic_boolean" id="0U=r86[k|[A~`qoNg2pL"><field name="BOOL">FALSE</field></shadow></value></block></statement></block><block type="component_event" id="d,{$;1wd#f3]Mf.](a`g" x="-3" y="657"><mutation xmlns="http://www.w3.org/1999/xhtml" component_name="Upload_photo" component_type="Button" parent_id="undefined" event_id="Click" was_updated="true"/><field name="component_id">ccda8fb5-7a81-4447-9d4a-34b32565d1ab</field><field name="event_id">Click</field><statement name="input_do"><block type="camera_select_photo_advanced" id="Z}:.IWvC(3{5{_nY)IWf" inline="false"><mutation xmlns="http://www.w3.org/1999/xhtml" show_callback_params="true" callback_params_added="true"/><field name="MEDIA_TYPE_OPTIONS">PHOTO</field><value name="CALLBACK_PARAM0"><block type="callback_arg" id="DQRJK$M;_b#o1fTZ;YLr"><mutation xmlns="http://www.w3.org/1999/xhtml" tooltip="" language_neutral_name="photo" arg_name_trans_key="blocks.camera.select_photo.photo_or_video" old_arg_name="photo or video"/></block></value><value name="CALLBACK_PARAM1"><block type="callback_arg" id="kIhFElN$,en+!bGDt}4$"><mutation xmlns="http://www.w3.org/1999/xhtml" tooltip="" language_neutral_name="cancel" arg_name_trans_key="blocks.camera.select_photo.cancel" old_arg_name="was cancelled"/></block></value><value name="CALLBACK_PARAM2"><block type="callback_arg" id="!tV94S%;p4xStk8d*:kT"><mutation xmlns="http://www.w3.org/1999/xhtml" tooltip="" language_neutral_name="error" arg_name_trans_key="blocks.camera.error" old_arg_name="error"/></block></value><statement name="DO"><block type="controls_if" id="A}ErjcPm[8AggdKP.1@~"><value name="IF0"><block type="logic_negate" id="t:3_JI}anR3ISO?[`QhW"><value name="BOOL"><block type="callback_arg" id="SO8Y7P$vF+H]bf:5?OaM"><mutation xmlns="http://www.w3.org/1999/xhtml" tooltip="" language_neutral_name="cancel" arg_name_trans_key="blocks.camera.take_photo.cancel" old_arg_name="was cancelled" is_detached_parameter="true"/></block></value></block></value><statement name="DO0"><block type="controls_if" id="Ww8l8o$oq6~328qWct#0"><mutation else="1"/><statement name="DO0"><block type="setter" id="DF]8_+|SA9OCiv;.L2?n"><mutation xmlns="http://www.w3.org/1999/xhtml" component_name="Profile Screen Error Label" parent_id="undefined"/><field name="component_id">4282b87d-6e30-4676-a6fe-507531ac775f</field><field name="field_name">Text</field><value name="field_value"><shadow type="text" id="PDN,gBm~eoaM4jHfHy;G"><field name="TEXT">Name cannot be blank.</field></shadow><block type="callback_arg" id="[u:oylLkd@!}E7kcW$TA"><mutation xmlns="http://www.w3.org/1999/xhtml" tooltip="" language_neutral_name="error" arg_name_trans_key="blocks.sound.error" old_arg_name="error" is_detached_parameter="true"/></block></value></block></statement><statement name="ELSE"><block type="camera_upload_image_advanced" id="u!,Su8W|)k=e4^z(ELM|" inline="false"><mutation xmlns="http://www.w3.org/1999/xhtml" show_callback_params="true" callback_params_added="true"/><value name="IMAGE"><shadow type="asset_get" id="2$O%.yS-xJcc$)lbkggy"><mutation xmlns="http://www.w3.org/1999/xhtml" previous_asset_name="" previous_asset_value="INVALID_ASSET"/><field name="ASSET">INVALID_ASSET</field></shadow><block type="callback_arg" id="i[096^_dZ~`Ym4z5ZB?K"><mutation xmlns="http://www.w3.org/1999/xhtml" tooltip="" language_neutral_name="photo" arg_name_trans_key="blocks.camera.take_photo.photo" old_arg_name="photo" is_detached_parameter="true"/></block></value><value name="CALLBACK_PARAM0"><block type="callback_arg" id="(}tSJz_WRaryoiICx!:Q"><mutation xmlns="http://www.w3.org/1999/xhtml" tooltip="" language_neutral_name="url" arg_name_trans_key="blocks.camera.upload_image.url" old_arg_name="url"/></block></value><value name="CALLBACK_PARAM1"><block type="callback_arg" id="m+)}9DYMkUXC_W`a-5~T"><mutation xmlns="http://www.w3.org/1999/xhtml" tooltip="" language_neutral_name="error" arg_name_trans_key="blocks.sound.error" old_arg_name="error"/></block></value><statement name="DO"><block type="controls_if" id="?0%0jyoT*^DR!TdPLxqc"><mutation else="1"/><value name="IF0"><block type="callback_arg" id="9$^E`}g6!`PJHRiehyM-"><mutation xmlns="http://www.w3.org/1999/xhtml" tooltip="" language_neutral_name="error" arg_name_trans_key="blocks.sound.error" old_arg_name="error" is_detached_parameter="true"/></block></value><statement name="DO0"><block type="setter" id="ryxn7.`L$=p.Id0Pe`=f"><mutation xmlns="http://www.w3.org/1999/xhtml" component_name="Profile Screen Error Label" parent_id="undefined"/><field name="component_id">4282b87d-6e30-4676-a6fe-507531ac775f</field><field name="field_name">Text</field><value name="field_value"><shadow type="text" id="PDN,gBm~eoaM4jHfHy;G"><field name="TEXT">Name cannot be blank.</field></shadow><block type="callback_arg" id="6BpK63AjqM{j!Z0cd+Xe"><mutation xmlns="http://www.w3.org/1999/xhtml" tooltip="" language_neutral_name="error" arg_name_trans_key="blocks.sound.error" old_arg_name="error" is_detached_parameter="true"/></block></value></block></statement><statement name="ELSE"><block type="variables_set_dynamic" id="+F]EmBE/!2?jE%I+rlf1"><field name="SCOPE">CLOUD</field><value name="NAME"><shadow type="text" id="DUn@w(VZbDQ~+B[etM,U"><field name="TEXT">name</field></shadow><block type="text_join" id="(}mn|e(0#B=rPOV?wJaX"><mutation items="2"/><value name="ADD0"><block type="variables_get" id="cOKNBs7C?GjP7|p|e[=v"><mutation xmlns="http://www.w3.org/1999/xhtml" saved_name="app variable session_id"/><field name="VAR">9e995ff8-a9a5-4978-b428-d429d0843a1d</field></block></value><value name="ADD1"><block type="text" id="-1N5~07)YL{UlkeNg}+7"><field name="TEXT">/Image</field></block></value></block></value><value name="VALUE"><block type="callback_arg" id="I6{WTRo$YcG]mH8aiO{~"><mutation xmlns="http://www.w3.org/1999/xhtml" tooltip="" language_neutral_name="url" arg_name_trans_key="blocks.camera.upload_image.url" old_arg_name="url" is_detached_parameter="true"/></block></value><next><block type="setter" id="99Z`8E)+t@5B+z4bm+xH"><mutation xmlns="http://www.w3.org/1999/xhtml" component_name="Profile_Pic" parent_id="undefined"/><field name="component_id">dd25b85d-4fa8-4729-ac41-0a5f4f772617</field><field name="field_name">Picture</field><value name="field_value"><shadow type="asset_get" id="6{d6G_Ib.zR3Q_{/b7~J"><mutation xmlns="http://www.w3.org/1999/xhtml" previous_asset_name="" previous_asset_value="INVALID_ASSET"/><field name="ASSET">INVALID_ASSET</field></shadow><block type="variables_get_dynamic" id="c0Oyl0*lZe*c2t%.Rul;"><field name="SCOPE">CLOUD</field><value name="NAME"><shadow type="text" id="m5.?kQ}.7lO8.Q+LbnzW"><field name="TEXT">name</field></shadow><block type="text_join" id="V{@C$v3_`Esw/q6I%5ar"><mutation items="2"/><value name="ADD0"><block type="variables_get" id="=3VUQ}LntmVr=(ehU,yy"><mutation xmlns="http://www.w3.org/1999/xhtml" saved_name="app variable session_id"/><field name="VAR">9e995ff8-a9a5-4978-b428-d429d0843a1d</field></block></value><value name="ADD1"><block type="text" id="clHB,^nrM17nqy,3@-,f"><field name="TEXT">/Image</field></block></value></block></value></block></value><next><block type="setter" id="oOB5?^ANx/8_-(:4!r?,"><mutation xmlns="http://www.w3.org/1999/xhtml" component_name="Image Group" parent_id="undefined"/><field name="component_id">494cdfac-e3d7-4df9-977c-4a9a8e71b920</field><field name="field_name">Visible</field><value name="field_value"><shadow type="logic_boolean" id="R.t{j{tXPHH3Z/vMCofl"><field name="BOOL">FALSE</field></shadow></value></block></next></block></next></block></statement></block></statement></block></statement></block></statement></block></statement></block></statement></block><block type="component_event" id="1#qX/)0E^|14D(`t6tP2" x="936" y="664"><mutation xmlns="http://www.w3.org/1999/xhtml" component_name="Take_photo" component_type="Button" parent_id="undefined" event_id="Click" was_updated="true"/><field name="component_id">96a81084-1379-4702-9d92-dee0ad4ce423</field><field name="event_id">Click</field><statement name="input_do"><block type="camera_take_photo_advanced" id="|R00ZuQT~U(FF-%~uul:" inline="false"><mutation xmlns="http://www.w3.org/1999/xhtml" show_callback_params="true" callback_params_added="true"/><value name="CALLBACK_PARAM0"><block type="callback_arg" id="Au%f.UWN}f7TPmALLf*)"><mutation xmlns="http://www.w3.org/1999/xhtml" tooltip="" language_neutral_name="photo" arg_name_trans_key="blocks.camera.take_photo.photo" old_arg_name="photo"/></block></value><value name="CALLBACK_PARAM1"><block type="callback_arg" id="]yNNKQOCjfQ,Bq!t?I9F"><mutation xmlns="http://www.w3.org/1999/xhtml" tooltip="" language_neutral_name="cancel" arg_name_trans_key="blocks.camera.take_photo.cancel" old_arg_name="was cancelled"/></block></value><value name="CALLBACK_PARAM2"><block type="callback_arg" id="D~ORq[b`0)2PWv(tg*^y"><mutation xmlns="http://www.w3.org/1999/xhtml" tooltip="" language_neutral_name="error" arg_name_trans_key="blocks.sound.error" old_arg_name="error"/></block></value><statement name="DO"><block type="controls_if" id="#VmS?$5OzC4HRmy}wtb*"><value name="IF0"><block type="logic_negate" id="6Znvfw[U?xkFwE6E%}Y9"><value name="BOOL"><block type="callback_arg" id="*]([$OB!Q!rR+o[N*Z-/"><mutation xmlns="http://www.w3.org/1999/xhtml" tooltip="" language_neutral_name="cancel" arg_name_trans_key="blocks.camera.take_photo.cancel" old_arg_name="was cancelled" is_detached_parameter="true"/></block></value></block></value><statement name="DO0"><block type="controls_if" id="gS[`Kr^=li/BBumpb^=j"><mutation else="1"/><statement name="DO0"><block type="setter" id="MIV8d0|L#|uUyHMUapy7"><mutation xmlns="http://www.w3.org/1999/xhtml" component_name="Profile Screen Error Label" parent_id="undefined"/><field name="component_id">4282b87d-6e30-4676-a6fe-507531ac775f</field><field name="field_name">Text</field><value name="field_value"><shadow type="text" id="PDN,gBm~eoaM4jHfHy;G"><field name="TEXT">Name cannot be blank.</field></shadow><block type="callback_arg" id="7]$],TXjA#yl.tSWWo[C"><mutation xmlns="http://www.w3.org/1999/xhtml" tooltip="" language_neutral_name="error" arg_name_trans_key="blocks.sound.error" old_arg_name="error" is_detached_parameter="true"/></block></value></block></statement><statement name="ELSE"><block type="camera_upload_image_advanced" id="_^%tt;`f`P-xhL:-n}Lu" inline="false"><mutation xmlns="http://www.w3.org/1999/xhtml" show_callback_params="true" callback_params_added="true"/><value name="IMAGE"><shadow type="asset_get" id="2$O%.yS-xJcc$)lbkggy"><mutation xmlns="http://www.w3.org/1999/xhtml" previous_asset_name="" previous_asset_value="INVALID_ASSET"/><field name="ASSET">INVALID_ASSET</field></shadow><block type="callback_arg" id="09~ZnDfD~8r8CL(#!yh,"><mutation xmlns="http://www.w3.org/1999/xhtml" tooltip="" language_neutral_name="photo" arg_name_trans_key="blocks.camera.take_photo.photo" old_arg_name="photo" is_detached_parameter="true"/></block></value><value name="CALLBACK_PARAM0"><block type="callback_arg" id="T4.[e$LjSOhA-/R7IF]w"><mutation xmlns="http://www.w3.org/1999/xhtml" tooltip="" language_neutral_name="url" arg_name_trans_key="blocks.camera.upload_image.url" old_arg_name="url"/></block></value><value name="CALLBACK_PARAM1"><block type="callback_arg" id=",mE4J/`V23fdtQ97v*X]"><mutation xmlns="http://www.w3.org/1999/xhtml" tooltip="" language_neutral_name="error" arg_name_trans_key="blocks.sound.error" old_arg_name="error"/></block></value><statement name="DO"><block type="controls_if" id="6u{l{}=8PtXPf$G=4ES$"><mutation else="1"/><value name="IF0"><block type="callback_arg" id="7=ruT{0#_YBov~Ojg]b5"><mutation xmlns="http://www.w3.org/1999/xhtml" tooltip="" language_neutral_name="error" arg_name_trans_key="blocks.sound.error" old_arg_name="error" is_detached_parameter="true"/></block></value><statement name="DO0"><block type="setter" id="4-^lBzL4n_JD:6?IV_:~"><mutation xmlns="http://www.w3.org/1999/xhtml" component_name="Profile Screen Error Label" parent_id="undefined"/><field name="component_id">4282b87d-6e30-4676-a6fe-507531ac775f</field><field name="field_name">Text</field><value name="field_value"><shadow type="text" id="PDN,gBm~eoaM4jHfHy;G"><field name="TEXT">Name cannot be blank.</field></shadow><block type="callback_arg" id="#hia{~EkDTyy2+LWSy^)"><mutation xmlns="http://www.w3.org/1999/xhtml" tooltip="" language_neutral_name="error" arg_name_trans_key="blocks.sound.error" old_arg_name="error" is_detached_parameter="true"/></block></value></block></statement><statement name="ELSE"><block type="variables_set_dynamic" id="y%a/w;4+_3Vy%Fxo]cQd"><field name="SCOPE">CLOUD</field><value name="NAME"><shadow type="text" id="DUn@w(VZbDQ~+B[etM,U"><field name="TEXT">name</field></shadow><block type="text_join" id="]d#-I|zd6RZ$s3nKwv_q"><mutation items="2"/><value name="ADD0"><block type="variables_get" id="D[lkHYc(Oo6Q8=jAt4~l"><mutation xmlns="http://www.w3.org/1999/xhtml" saved_name="app variable session_id"/><field name="VAR">9e995ff8-a9a5-4978-b428-d429d0843a1d</field></block></value><value name="ADD1"><block type="text" id="G*{?yA^@Q9|V1.3UM.l|"><field name="TEXT">/Image</field></block></value></block></value><value name="VALUE"><block type="callback_arg" id="3U;wlbMHd`BX4_9EB[V^"><mutation xmlns="http://www.w3.org/1999/xhtml" tooltip="" language_neutral_name="url" arg_name_trans_key="blocks.camera.upload_image.url" old_arg_name="url" is_detached_parameter="true"/></block></value><next><block type="setter" id="$@X0#e-xrE1b{}E%#K!G"><mutation xmlns="http://www.w3.org/1999/xhtml" component_name="Profile_Pic" parent_id="undefined"/><field name="component_id">dd25b85d-4fa8-4729-ac41-0a5f4f772617</field><field name="field_name">Picture</field><value name="field_value"><shadow type="asset_get" id="6{d6G_Ib.zR3Q_{/b7~J"><mutation xmlns="http://www.w3.org/1999/xhtml" previous_asset_name="" previous_asset_value="INVALID_ASSET"/><field name="ASSET">INVALID_ASSET</field></shadow><block type="variables_get_dynamic" id="o(gS3%O~8EL!j?HSeqkD"><field name="SCOPE">CLOUD</field><value name="NAME"><shadow type="text" id="m5.?kQ}.7lO8.Q+LbnzW"><field name="TEXT">name</field></shadow><block type="text_join" id="7r2~_D6/8hC*(I~_NeMz"><mutation items="2"/><value name="ADD0"><block type="variables_get" id="m;UsED`atL@,GvU]Xj`u"><mutation xmlns="http://www.w3.org/1999/xhtml" saved_name="app variable session_id"/><field name="VAR">9e995ff8-a9a5-4978-b428-d429d0843a1d</field></block></value><value name="ADD1"><block type="text" id="Re=f.Tqmyi+o(r3DRGQI"><field name="TEXT">/Image</field></block></value></block></value></block></value><next><block type="setter" id="T69L?nohGt*qDYwKp7(w"><mutation xmlns="http://www.w3.org/1999/xhtml" component_name="Image Group" parent_id="undefined"/><field name="component_id">494cdfac-e3d7-4df9-977c-4a9a8e71b920</field><field name="field_name">Visible</field><value name="field_value"><shadow type="logic_boolean" id="nzQ@@)j5%Q:UK`r{?g`G"><field name="BOOL">FALSE</field></shadow></value></block></next></block></next></block></statement></block></statement></block></statement></block></statement></block></statement></block></statement></block></xml>